TransProPy/AutoFeatureSelection.py
TransProPy/AutogluonSelectML.py
TransProPy/AutogluonTimeLimit.py
TransProPy/MACFCmain.py
TransProPy/NewMACFCmain.py
TransProPy/__init__.py
TransProPy/UtilsFunction1/Auc.py
TransProPy/UtilsFunction1/AutoNorm.py
TransProPy/UtilsFunction1/FeatureRanking.py
TransProPy/UtilsFunction1/FilterSamples.py
TransProPy/UtilsFunction1/GeneNames.py
TransProPy/UtilsFunction1/GeneToFeatureMapping.py
TransProPy/UtilsFunction1/LoadData.py
TransProPy/UtilsFunction1/NewFeatureRanking.py
TransProPy/UtilsFunction1/PrintResults.py
TransProPy/UtilsFunction1/__init__.py
TransProPy/UtilsFunction2/LogTransform.py
TransProPy/UtilsFunction2/__init__.py
TransProPy/UtilsFunction2/splitdata.py
TransProPy/UtilsFunction3/EnsembleForRFE.py
TransProPy/UtilsFunction3/ExtractAndSaveResults.py
TransProPy/UtilsFunction3/ExtractCommonSamples.py
TransProPy/UtilsFunction3/LoadAndPreprocessData.py
TransProPy/UtilsFunction3/LoadEncodeLabels.py
TransProPy/UtilsFunction3/LoadFilterTranspose.py
TransProPy/UtilsFunction3/LoggingCustomScorer.py
TransProPy/UtilsFunction3/PrintBoxedText.py
TransProPy/UtilsFunction3/SetupFeatureSelection.py
TransProPy/UtilsFunction3/SetupLoggingAndProgressBar.py
TransProPy/UtilsFunction3/TqdmCustomScorer.py
TransProPy/UtilsFunction3/TrainModel.py
TransProPy/UtilsFunction3/UpdateProgressBar.py
TransProPy/UtilsFunction3/__init__.py
transpropy-1.0.0.dist-info/LICENSE
transpropy-1.0.0.dist-info/METADATA
transpropy-1.0.0.dist-info/WHEEL
transpropy-1.0.0.dist-info/top_level.txt
transpropy-1.0.0.dist-info/RECORD
