Metadata-Version: 2.1
Name: transpropy
Version: 1.0.0
Summary: A collection of deep learning models that integrate algorithms and various machine learning approaches to extract features (genes) effective for classification and attribute them accordingly.
Home-page: https://github.com/SSSYDYSSS/TransProPy
Author: Yu Dongyue
Author-email: yudongyue@mail.nankai.edu.cn
License-File: LICENSE
Requires-Dist: numpy
Requires-Dist: pandas
Requires-Dist: setuptools
Requires-Dist: scikit-learn
Requires-Dist: tqdm
